kxy_datasets/__init__.py
kxy_datasets/base.py
kxy_datasets/classifications.py
kxy_datasets/kaggle_classifications.py
kxy_datasets/kaggle_regressions.py
kxy_datasets/regressions.py
kxy_datasets/synthetic_classifications.py
kxy_datasets/synthetic_regressions.py
kxy_datasets/uci_classifications.py
kxy_datasets/uci_regressions.py
kxy_datasets/utils.py
kxy_datasets/value_datasets.py
kxy_datasets-0.0.14.dist-info/METADATA
kxy_datasets-0.0.14.dist-info/WHEEL
kxy_datasets-0.0.14.dist-info/top_level.txt
kxy_datasets-0.0.14.dist-info/RECORD
